setup.py
tests/__init__.py
tests/acceptance/__init__.py
tests/acceptance/base.py
tests/acceptance/test_default.py
tests/acceptance/test_target.py
tests/unit/__init__.py
tests/unit/base.py
tests/unit/test_user_data_model.py
tests/unit/cli/__init__.py
tests/unit/cli/test_app.py
tests/unit/cli/test_auth_controller.py
tests/unit/cli/test_cli_base_controller.py
tests/unit/cli/test_default_controller.py
tests/unit/cli/test_load_test_controller.py
tests/unit/cli/test_main.py
tests/unit/cli/test_project_controller.py
tests/unit/cli/test_target_controller.py
tests/unit/cli/test_team_controller.py
tests/unit/cli/test_user_controller.py
wight/__init__.py
wight/errors.py
wight/models.py
wight/cli/__init__.py
wight/cli/app.py
wight/cli/auth.py
wight/cli/base.py
wight/cli/config.py
wight/cli/default.py
wight/cli/load_test.py
wight/cli/project.py
wight/cli/target.py
wight/cli/team.py
wight/cli/user.py
wight_cli.egg-info/PKG-INFO
wight_cli.egg-info/SOURCES.txt
wight_cli.egg-info/dependency_links.txt
wight_cli.egg-info/entry_points.txt
wight_cli.egg-info/requires.txt
wight_cli.egg-info/top_level.txt